joystickduino/__init__.py
joystickduino/__main__.py
joystickduino-0.0.4.dist-info/METADATA
joystickduino-0.0.4.dist-info/WHEEL
joystickduino-0.0.4.dist-info/top_level.txt
joystickduino-0.0.4.dist-info/RECORD
