Metadata-Version: 2.1
Name: joystickduino
Version: 0.0.4
Summary: may the force be with you
Home-page: UNKNOWN
Author: Someone
Author-email: shaurya.p.singh21@gmail.com
License: UNKNOWN
Platform: UNKNOWN
Requires-Dist: pyserial
Requires-Dist: pyautogui
